mitmproxy2swagger/__init__.py
mitmproxy2swagger/console_util.py
mitmproxy2swagger/har_capture_reader.py
mitmproxy2swagger/http_util.py
mitmproxy2swagger/mitmproxy2swagger.py
mitmproxy2swagger/mitmproxy2swagger_bk.py
mitmproxy2swagger/mitmproxy2swagger_m.py
mitmproxy2swagger/mitmproxy_capture_reader.py
mitmproxy2swagger/swagger_util.py
mitmproxy2swagger/test.py
mitmproxy2swagger/test_mitmproxy2swagger.py
mitmproxy2swagger/test_openapi_compliance.py
mitmproxy2swagger/testing_util.py
m2s-0.14.7.dist-info/METADATA
m2s-0.14.7.dist-info/WHEEL
m2s-0.14.7.dist-info/entry_points.txt
m2s-0.14.7.dist-info/RECORD
