Metadata-Version: 2.4
Name: m2s
Version: 0.14.7
Summary: 
License: MIT
Author: z2y
Author-email: jiyvn.liu@aliyun.com
Requires-Python: >=3.10,<4.0
Classifier: License :: OSI Approved :: MIT License
Classifier: Programming Language :: Python :: 3
Classifier: Programming Language :: Python :: 3.10
Classifier: Programming Language :: Python :: 3.11
Classifier: Programming Language :: Python :: 3.12
Classifier: Programming Language :: Python :: 3.13
Classifier: Programming Language :: Python :: 3.14
Requires-Dist: json-stream (>=2.3.2,<3.0.0)
Requires-Dist: mitmproxy (>=11.0.2,<12.0.0)
Requires-Dist: msgpack (>=1.0.7,<2.0.0)
Requires-Dist: ruamel.yaml (>=0.17.32,<0.19.0)
